say_igna/__init__.py
say_igna/a.py
say_igna/hello.py
say_igna-0.0.5.dist-info/METADATA
say_igna-0.0.5.dist-info/WHEEL
say_igna-0.0.5.dist-info/top_level.txt
say_igna-0.0.5.dist-info/RECORD
