Metadata-Version: 2.1
Name: say-igna
Version: 0.0.5
Summary: Descripción paquete pip
Home-page: UNKNOWN
Author: Ignacio Mendiola Rodriguez
Author-email: <ignamendi21@gmail.com>
License: UNKNOWN
Platform: UNKNOWN
